{
  "name": "姑娘的物欲",
  "title": "姑娘的物欲",
  "author": "廖汉斯（University of Michigan Ann Arbor）",
  "subject": "",
  "column": "",
  "intro": "**俗话说女孩要富养，免得以后太容易被诱惑，这话不是完全没有道理。作为一个正常的女孩子，纱裙子、运动服和白睡衣这三件芝麻小事能够在我脑海里印下难以磨灭的印记，更...",
  "keywords": [
    "天璇",
    "廖汉斯（University of Michigan Ann Arbor）",
    "廖汉斯（University of Michigan Ann Arbor）：【痴人说梦",
    "校服",
    "姑娘",
    "生活",
    "欲望、廖汉斯、痴人说梦",
    "时尚"
  ],
  "cover": "2fde5374-62f6-4112-8b1e-12c982c9c254.jpg",
  "date": "2012-07-23T12:00:18.000Z"
}
