{
  "name": "【用脊椎骨阅读】曲高而和不寡：当代知识分子的独立与自由——以胡适、陈寅恪与王元化为例",
  "title": "曲高而和不寡：当代知识分子的独立与自由——以胡适、陈寅恪与王元化为例",
  "author": "李峻杰（暨南大学）",
  "subject": "用脊椎骨阅读",
  "column": "",
  "intro": "为自己思想信仰的结果负责任，不怕“监禁杀头”，只认得真理，乃是中国知识分子最应该坚守的操守。而对权力的俯首帖耳，则会失去最本质的学术，最本质的人格。",
  "keywords": [
    "尊严",
    "为学频道",
    "曲高而和不寡：当代知识分子的独立与自由——以胡适、陈寅恪与王元化为例",
    "自由",
    "李峻杰",
    "为学",
    "李峻杰（暨南大学）",
    "用脊椎骨阅读",
    "学术",
    "人物",
    "独立"
  ],
  "cover": "8f3fb2dc-3e13-499f-9e72-0b1aec2fabd4.jpg",
  "date": "2013-06-01T12:00:05.000Z"
}
