{
  "name": "【青年行动】女权青年在行动：向一切性别不公说“不”——“we关注”系列公益沙龙第三期文字记录",
  "title": "女权青年在行动：向一切性别不公说“不”——“we关注”系列公益沙龙第三期文字记录",
  "author": "董丽蒙  706青年空间",
  "subject": "青年行动",
  "column": "",
  "intro": "我们需要女权主义吗？中国实现性别平等了吗？中国的性别差异和性别歧视又体现在哪些方面？带着这些问题，本期“WE关注”我们一起聆听那些女权主义者们的昔日经历与她们对于女权问题的深刻感悟。",
  "keywords": [
    "最新人文公益资讯",
    "性别平等",
    "北京",
    "女权",
    "董丽蒙  706青年空间",
    "最新公益类实践资讯",
    "女权青年在行动：向一切性别不公说“不”——“we关注”系列公益沙龙第三期文字记录",
    "青年行动",
    "706青年空间"
  ],
  "cover": "29059407-e072-4f0b-a852-27ccb79d933d.jpg",
  "date": "2013-09-09T12:00:00.000Z"
}
